[
{
  "id": "khilafa",
  "title": "খিলাফাহ",
  "author": "ইমরান রাইহান",
  "cover": "https://wafilife-media.wafilife.com/uploads/2025/09/%E0%A6%96%E0%A6%BF%E0%A6%B2%E0%A6%BE%E0%A6%AB%E0%A6%BE%E0%A6%B9-250x375.jpg",
  "description": "ইসলামী খেলাফতের উত্থান-পতন, ঐতিহাসিক প্রেক্ষাপট এবং মুসলিম উম্মাহর শাসনব্যবস্থার গৌরবময় ইতিহাস নিয়ে রচিত একটি চমৎকার গবেষণামূলক বই।",
  "categories": ["ধর্ম", "ইতিহাস"],
  "status": "পড়বো",
  "storeLink": "https://rkmri.co/meTRSpReR2Te/",
  "review": "খেলাফতের ইতিহাস ও এর রাজনৈতিক প্রেক্ষাপট সম্পর্কে জানার জন্য বইটি পড়ার তালিকায় যুক্ত করলাম।",
  "year": 2026,
  "priority": 5
},

{
  "id": "mubasshirin-1st-part",
  "title": "মুবাশশিরীন প্রথম খন্ড",
  "author": "জিম তানভীর",
  "cover": "https://wafilife-media.wafilife.com/uploads/2026/02/mubasshirin-250x387.jpg",
  "description": "পবিত্র কুরআনে বর্ণিত আল্লাহ সুবহানাহু ওয়া তাআলা প্রেরিত নবী ও রাসূলগণের পবিত্র জীবন, দাওয়াত এবং ঐতিহাসিক ঘটনাবলি নিয়ে রচিত একটি শিক্ষণীয় বই।",
  "categories": ["ধর্ম", "ইতিহাস"],
  "status": "পড়ছি",
  "storeLink": "https://rkmri.co/0R2o52AemmNE/",
  "review": "বইটি বর্তমানে পড়ছি। নবী-রাসূলদের জীবন এবং ইসলামের ইতিহাস সম্পর্কে জানার জন্য এটি চমৎকার একটি বই।",
  "year": 2026,
  "priority": 5
},

{
  "id": "ek-nojore-quran",
  "title": "এক নজরে কুরআন",
  "author": "ড. মিজানুর রহমান আজহারি",
  "cover": "https://wafilife-media.wafilife.com/uploads/2025/02/%E0%A6%8F%E0%A6%95-%E0%A6%A8%E0%A6%9C%E0%A6%B0%E0%A7%87-%E0%A6%95%E0%A6%AD%E0%A6%BE%E0%A6%B0-250x361.jpg",
  "description": "পবিত্র কুরআনের ১১৪টি সূরার সংক্ষিপ্ত পরিচিতি, অবতীর্ণের সময়, নামকরণের পটভূমি এবং মূল বিষয়বস্তু অত্যন্ত সহজ ও সাবলীল ভাষায় তুলে ধরা হয়েছে এই বইটিতে।",
  "categories": ["ধর্ম"],
  "status": "পড়া শেষ",
  "storeLink": "https://rkmri.co/eeNMIN0oIAlM/",
  "review": "বইটি পড়া শেষ হয়েছে। পবিত্র কুরআনের মৌলিক বিষয়গুলো এক নজরে এবং সহজে জানার জন্য এটি বেশ কার্যকর ও তথ্যবহুল একটি বই।",
  "year": 2026,
  "priority": 5
},

{
  "id": "rahe-belayet",
  "title": "রাহে বেলায়াত",
  "author": "ড. খোন্দকার আব্দুল্লাহ জাহাঙ্গীর",
  "cover": "https://wafilife-media.wafilife.com/uploads/2015/05/rahe-belayet.-250x394.jpg",
  "description": "কুরআন ও সহীহ হাদীসের আলোকে যিকির ও দুআর প্রকৃত পদ্ধতি এবং রাসূল (সা.) এর দেখানো সহীহ পন্থায় আল্লাহর নৈকট্য অর্জনের পথ নিয়ে রচিত একটি গুরুত্বপূর্ণ বই।",
  "categories": ["ধর্ম","আত্মশুদ্ধি"],
  "status": "পড়বো",
  "storeLink": "https://rkmri.co/MApEel0yoMlA/",
  "review": "এখনো পড়া হয়নি, তবে এটি একটি অত্যন্ত জনপ্রিয় এবং সমৃদ্ধ বই হিসেবে পরিচিত।",
  "year": 2026,
  "priority": 1
},

{
  "id": "hadise-rasul-saw",
  "title": "হাদীসে রাসূল (সাঃ) প্রয়োজনীয়та ও প্রামাণ্যতা",
  "author": "ড. খোন্দকার আব্দুল্লাহ জাহাঙ্গীর",
  "cover": "https://wafilife-media.wafilife.com/uploads/2024/12/Scan_20241203-10-250x385.jpg",
  "description": "ইসলামী শরীয়তের অন্যতম প্রধান উৎস হাদীস ও সুন্নাহর গুরুত্ব, মানব জীবনে এর প্রয়োজনীয়তা এবং আইনি প্রামাণ্যতার বিষয়ে ড. খোন্দকার আব্দুল্লাহ জাহাঙ্গীর (রহ.) এর একটি চমৎকার গবেষণামূলক বই।",
  "categories": ["ধর্ম"],
  "status": "পড়া শেষ",
  "storeLink": "https://rkmri.co/NAeeI02epeEM/",
  "review": "বইটি পড়া শেষ হয়েছে। হাদীস ও সুন্নাহর গুরুত্ব এবং প্রামাণ্যতা সম্পর্কে স্পষ্ট ধারণা পাওয়ার জন্য এটি অত্যন্ত গুরুত্বপূর্ণ ও দলিলভিত্তিক একটি বই।",
  "year": 2026,
  "priority": 5
},

{
  "id": "allahor-pothe-dawat",
  "title": "আল্লাহর পথে দাওয়াত",
  "author": "ড. খোন্দকার আব্দুল্লাহ জাহাঙ্গীর",
  "cover": "https://wafilife-media.wafilife.com/uploads/2016/07/0-250x390.jpg",
  "description": "ইসলামের সঠিক বার্তা মানুষের কাছে পৌঁছে দেওয়ার সঠিক পদ্ধতি, দাওয়াতের গুরুত্ব, ফজিলত এবং হিকমত বা প্রজ্ঞা নিয়ে কুরআন ও সুন্নাহর আলোকে একটি যুগোপযোগী ও দিকনির্দেশনামূলক বই।",
  "categories": ["ধর্ম"],
  "status": "পড়া শেষ",
  "storeLink": "https://rkmri.co/eeMASSee5MM3/",
  "review": "বইটি পড়া শেষ হয়েছে। ইসলামের শাশ্বত বাণী মানুষের কাছে সুন্দর ও কার্যকর পন্থায় পৌঁছে দেওয়ার ক্ষেত্রে এটি একটি অসাধারণ বই।",
  "year": 2026,
  "priority": 5
},

{
  "id": "lavay-lalshak-puber-akash",
  "title": "লাভায় লালশাক পুবের আকাশ",
  "author": "ওসমান হাদি",
  "cover": "https://wafilife-media.wafilife.com/uploads/2026/03/lavay_lalshak1-250x390.png",
  "description": "সমকালীন সমাজ, মানুষের জীবনবোধ এবং তীব্র আবেগ-অনুভূতির মেলবন্ধনে রচিত একটি অনবদ্য কাব্যগ্রন্থ ও কবিতার সংকলন।",
  "categories": ["বাংলা সাহিত্য"],
  "status": "পড়া শেষ",
  "storeLink": "https://rkmri.co/Ay52eARNeRl0/",
  "review": "বইটি পড়া শেষ হয়েছে। এর কবিতাগুলোর প্রকাশভঙ্গি ও গভীর জীবনবোধ সত্যি হৃদয়স্পর্শী।",
  "year": 2026,
  "priority": 5
},
{
  "id": "sirah-1st-part",
  "title": "সীরাহ (১ম খণ্ড)",
  "author": "জিম তানভীর",
  "cover": "https://wafilife-media.wafilife.com/uploads/2024/08/928342-IMG-250x389.jpg",
  "description": "রাসূলুল্লাহ সাল্লাল্লাহু আলাইহি ওয়াসাল্লাম-এর পবিত্র জীবন, নবুয়তের আগের আরব সমাজ এবং ইসলামের সূচনালগ্নের ঐতিহাসিক ঘটনাবলি নিয়ে অত্যন্ত সাবলীল ও নিখুঁত বিবরণ সংবলিত একটি অনবদ্য সীরাত গ্রন্থ।",
  "categories": ["ধর্ম", "ইতিহাস"],
  "status": "পড়া শেষ",
  "storeLink": "https://rkmri.co/00A23M0eA0Ao/",
  "review": "বইটি আগে পড়া শেষ হয়েছে। প্রিয় নবীজী (সা.)-এর জীবনকে সহজ ভাষায় ইতিহাসের নিখুঁত ধারাবাহিকতায় জানার জন্য এটি একটি চমৎকার বই।",
  "year": 2026,
  "priority": 5
},
{
  "id": "sirah-2nd-part",
  "title": "সীরাহ (২য় খণ্ড)",
  "author": "জিম তানভীর",
  "cover": "https://wafilife-media.wafilife.com/uploads/2024/08/348724-IMG-250x389.jpg",
  "description": "রাসূলুল্লাহ সাল্লাল্লাহু আলাইহি ওয়াসাল্লাম-এর মদীনা জীবনের গুরুত্বপূর্ণ ঘটনাবলি, ইসলামী রাষ্ট্রের প্রতিষ্ঠা, বিভিন্ন যুদ্ধ এবং ইসলামের চূড়ান্ত বিজয়ের নিখুঁত ও সাবলীল ধারাবাহিক বিবরণ সংবলিত সীরাত গ্রন্থ।",
  "categories": ["ধর্ম", "ইতিহাস"],
  "status": "পড়া শেষ",
  "storeLink": "https://rkmri.co/2mMTMMeeeM0N/",
  "review": "বইটি পড়া শেষ হয়েছে। ১ম খণ্ডের পর মদীনা জীবনের গৌরবময় ইতিহাস ও নবীজী (সা.)-এর আদর্শ রাষ্ট্র পরিচালনার রূপরেখা চমৎকারভাবে জানার জন্য এটি একটি অনবদ্য বই।",
  "year": 2026,
  "priority": 5
},
{
  "id": "muslimbongo",
  "title": "মুসলিমবঙ্গ",
  "author": "আসিফ আদনান",
  "cover": "https://wafilife-media.wafilife.com/uploads/2026/03/muslimbongo-250x390.png",
  "description": "বাংলার মুসলিম সমাজ, এ অঞ্চলের ইসলামের আগমন, প্রসার এবং মুসলিম উম্মাহর রাজনৈতিক ও সামাজিক রূপান্তরের এক অনবদ্য ঐতিহাসিক দলিল ও গবেষণামূলক বই।",
  "categories": ["ধর্ম", "ইতিহাস"],
  "status": "পড়া শেষ",
  "storeLink": "https://rkmri.co/EA2eNEAeMlS0/",
  "review": "বাংলার মুসলিমদের শেকড় এবং ইসলামের ইতিহাস বিস্তারিত জানতে বইটি পড়ার তালিকায় যুক্ত করলাম।",
  "year": 2026,
  "priority": 5
},
{
  "id": "the-story-of-muhammad",
  "title": "দ্য স্টোরি অব মুহাম্মদ",
  "author": "ড. মিরাজ মুহিউদ্দিন",
  "cover": "https://wafilife-media.wafilife.com/uploads/2026/01/font-250x390.png",
  "description": "বিশ্বনবী হযরত মুহাম্মদ সাল্লাল্লাহু আলাইহি ওয়াসাল্লাম-এর পবিত্র জীবনের ঘটনাবলি ও সীরাতের গুরুত্বপূর্ণ অধ্যায়গুলো নিয়ে একটি চমৎকার ও সহজবোধ্য বই।",
  "categories": ["ধর্ম", "ইতিহাস"],
  "status": "পড়ছি",
  "storeLink": "https://rkmri.co/oMyMyylyl3AM/",
  "review": "বইটি বর্তমানে পড়ছি। রাসূলুল্লাহ (সা.)-এর জীবনকে ভিন্ন আঙ্গিকে ও সহজভাবে জানার জন্য এটি দারুণ একটি বই।",
  "year": 2026,
  "priority": 5
},
{
  "id": "kitabul-mokaddos-injeel-sharif-o-lsayee-dharam",
  "title": "কিতাবুল মোকাদ্দস, ইঞ্জিল শরীফ ও ঈসায়ী ধর্ম",
  "author": "ড. খোন্দকার আব্দুল্লাহ জাহাঙ্গীর",
  "cover": "https://wafilife-media.wafilife.com/uploads/2018/11/0-1-4-250x390.jpg",
  "description": "Kitabul Mokaddos ebong Injeel Sharif-er bishleshorer pasapasi Christian missionary-der dhormoprocari rohonity o Itihas niye Dr. Khandaker Abdullah Jahangir (Rah.)-er ekti bishleshonatgok o gobeshonamulok boi.",
  "categories": ["ধর্ম"],
  "status": "পড়ছি",
  "storeLink": "https://rkmri.co/pM33Me5SMMTA/",
  "review": "Boi-ti bortomone podchi. Christian dhormo o missionary-der bhibhinno procar-poddhoti shomporke totthogoto dharona paoar jonno ekti proyojoniyo boi.",
  "year": 2026,
  "priority": 5
},
{
  "id": "destiny-disrupted",
  "title": "ডেসটিনি ডিসরাপ্টেড : ইসলামিক দৃষ্টিতে বিশ্ব ইতিহাস",
  "author": "তামিম আনসারী",
  "cover": "https://wafilife-media.wafilife.com/uploads/2020/08/IMG-20200708-WA0047-250x375.jpg",
  "description": "ইসলামের সূচনালগ্ন থেকে বর্তমান সময় পর্যন্ত মুসলিম বিশ্বের সামাজিক, রাজনৈতিক ও ঐতিহাসিক বিবর্তনের এক অনন্য বিশ্লেষণ, যা প্রাচ্য ও পাশ্চাত্যের ইতিহাসকে ভিন্ন এক দৃষ্টিকোণ থেকে তুলে ধরে।",
  "categories": ["ইতিহাস","ধর্ম" ],
  "status": "পড়বো",
  "storeLink": "https://rkmri.co/MT00R5RlyelE/",
  "review": "ইসলামিক দৃষ্টিকোণ থেকে বিশ্ব ইতিহাসের এক ভিন্ন রূপরেখা জানতে বইটি পড়ার তালিকায় যুক্ত করলাম।",
  "year": 2026,
  "priority": 5
},
{
  "id": "mutazila-itihash-o-droshon",
  "title": "মুতাজিলা : ইতিহাস ও দর্শন",
  "author": "পুলিন বকসী",
  "cover": "https://wafilife-media.wafilife.com/uploads/2023/03/Cover-Output-07.02.2023-1-250x407.jpg",
  "description": "ইসলামী চিন্তাধারার ইতিহাসে যুক্তিবাদী দল 'মুতাজিলা'র উৎপত্তি, বিকাশ, তাদের মূল দার্শনিক আকিদা ও মুসলিম সমাজে এর প্রভাব নিয়ে একটি তাত্ত্বিক আলোচনা।",
  "categories": ["ধর্ম", "ইতিহাস"],
  "status": "পড়বো",
  "storeLink": "https://rkmri.co/AlAASmooS5To/",
  "review": "ইসলামী দর্শন ও যুক্তিসংগত চিন্তার ইতিহাস জানতে বইটি পড়ার তালিকায় যুক্ত করলাম।",
  "year": 2026,
  "priority": 5
},
{
  "id": "abishwaser-bhanga-dewal",
  "title": "অবিশ্বাসের ভাঙা দেয়াল",
  "author": "সাজ্জাতুল মাওলা শান্ত",
  "cover": "https://wafilife-media.wafilife.com/uploads/2025/02/download-37-250x386.jpg",
  "description": "নাস্তিকতা ও সংশয়বাদের বিভিন্ন যুক্তি ও দর্শনের ব্যবচ্ছেদ এবং সমকালীন অবিশ্বাসের দেয়াল ভেঙে ইসলামের যৌক্তিক ও বুদ্ধিবৃত্তিক সত্যতা তুলে ধরার ক্ষেত্রে একটি চমৎকার বই।",
  "categories": ["ধর্ম"],
  "status": "পড়বো",
  "storeLink": "https://rkmri.co/ySo05RmM2e2N/",
  "review": "সমকালীন সংশয়বাদের বুদ্ধিবৃত্তিক জবাব ও বিশ্বাসের ভিত শক্ত করতে বইটি পড়ার তালিকায় যুক্ত করলাম।",
  "year": 2026,
  "priority": 5
},
{
  "id": "growing-through-struggle",
  "title": "Growing Through Struggle",
  "author": "ঝংকার মাহবুব",
  "cover": "https://rokbucket.rokomari.io/ProductNew20190903/260X372/Growing_Through_Struggle-Jhankar_Mahbub-854bc-378857.jpg",
  "description": "জীবনের নানামুখী প্রতিকূলতা, ব্যর্থতা ও মানসিক সংগ্রামকে কীভাবে ইতিবাচক শক্তিতে রূপান্তর করে ব্যক্তিগত ও ক্যারিয়ার জীবনে এগিয়ে যাওয়া যায়, তার এক অনুপ্রেরণামূলক ও বাস্তবসম্মত গাইডলাইন।",
  "categories": ["আত্মউন্নয়ন ও অনুপ্রেরণা"],
  "status": "পড়া শেষ",
  "storeLink": "https://rkmri.co/oI5SMMeANp3e/",
  "review": "বইটি পড়া শেষ হয়েছে। জীবনের কঠিন পরিস্থিতিগুলোতে ভেঙে না পড়ে কীভাবে আত্মবিশ্বাসের সাথে ঘুরে দাঁড়ানো যায়, সে বিষয়ে দারুণ কিছু বাস্তবসম্মত পরামর্শ রয়েছে এতে।",
  "year": 2026,
  "priority": 5
},
{
  "id": "quraner-shobdaboli",
  "title": "কুরআনের শব্দাবলী - ১",
  "author": "জোবায়ের আল মাহমুদ",
  "cover": "https://wafilife-media.wafilife.com/uploads/2022/06/quraner-shobdaboli.jpeg",
  "description": "পবিত্র কুরআনে ব্যবহৃত গুরুত্বপূর্ণ শব্দসমূহের অর্থ, ব্যাকরণগত বিশ্লেষণ এবং সহজ ব্যাখ্যা নিয়ে সংকলিত একটি চমৎকার বই, যা সাধারণ পাঠকদের জন্য অর্থসহ কুরআন অনুধাবন করা সহজ করে তোলে।",
  "categories": ["ধর্ম"],
  "status": "পড়বো",
  "storeLink": "https://rkmri.co/eeAAepleoIRe/",
  "review": "কুরআনের শব্দার্থ ও এর গভীর ভাবার্থ সহজে বোঝার জন্য বইটি পড়ার তালিকায় যুক্ত করলাম।",
  "year": 2026,
  "priority": 5
},
{
  "id": "quraner-shobdaboli",
  "title": "কুরআনের শব্দাবলী - ২",
  "author": "জোবায়ের আল মাহমুদ",
  "cover": "https://wafilife-media.wafilife.com/uploads/2022/09/WhatsApp-Image-2022-09-29-at-9.36.12-AM.jpeg",
  "description": "পবিত্র কুরআনে ব্যবহৃত গুরুত্বপূর্ণ শব্দসমূহের অর্থ, ব্যাকরণগত বিশ্লেষণ এবং সহজ ব্যাখ্যা নিয়ে সংকলিত একটি চমৎকার বই, যা সাধারণ পাঠকদের জন্য অর্থসহ কুরআন অনুধাবন করা সহজ করে তোলে।",
  "categories": ["ধর্ম"],
  "status": "পড়বো",
  "storeLink": "https://rkmri.co/TpMmmlMA5Io2/",
  "review": "কুরআনের শব্দার্থ ও এর গভীর ভাবার্থ সহজে বোঝার জন্য বইটি পড়ার তালিকায় যুক্ত করলাম।",
  "year": 2026,
  "priority": 5
},
{
  "id": "sharia-ki-bole-amra-ki-kori",
  "title": "শরীয়া কী বলে আমরা কী করি",
  "author": "হাসান মাহমুদ",
  "cover": "https://media.kitabghor.com/products/990/36148/4c1in1707636698lggb6ww.jpg",
  "description": "মুসলিম সমাজে প্রচলিত বিভিন্ন ধর্মীয় আচার-অনুষ্ঠান, সামাজিক প্রথা ও রীতিনীতির সাথে পবিত্র শরীয়তের প্রকৃত বিধানের যে বৈসাদৃশ্য ও দূরত্ব রয়েছে, তা কুরআন ও সুন্নাহর আলোকে ফুটিয়ে তোলার এক সংশোধনমূলক আলোচনা।",
  "categories": ["ধর্ম"],
  "status": "পড়া শেষ",
  "storeLink": "https://rkmri.co/NNMMEeeNpRlA/",
  "review": "বইটি আগে পড়া শেষ হয়েছে। আমাদের সমাজব্যবস্থায় ধর্মের নামে প্রচলিত ভুলগুলো সংশোধন করতে এবং শরীয়তের সঠিক বিধানগুলো জানতে এটি অত্যন্ত কার্যকরী একটি বই।",
  "year": 2026,
  "priority": 5
},
{
  "id": "ata-amr-dorshoner-notekhata-noy",
  "title": "এটা আমার দর্শনের নোটখাতা নয়",
  "author": "আরিফ রহমান",
  "cover": "https://m.media-amazon.com/images/S/compressed.photo.goodreads.com/books/1676739308i/122757255.jpg",
  "description": "দর্শন, সমাজ, ধর্ম ও মানব মনস্তত্ত্বের বিভিন্ন জটিল ও সূক্ষ্ম বিষয়গুলোকে সহজ ও প্রাঞ্জল ভাষায় ছোট ছোট চিন্তাভাবনা বা ভাবনার স্কেচ হিসেবে তুলে ধরার এক অনন্য বুদ্ধিবৃত্তিক প্রয়াস।",
  "categories": ["দর্শন", "মনস্তত্ত্ব"],
  "status": "পড়া শেষ",
  "storeLink": "https://rkmri.co/mNMTy0ART5Tp/",
  "review": "বইটি পড়া শেষ হয়েছে। দর্শন ও প্রাত্যহিক ভাবনার এক দারুণ সংমিশ্রণ, যা পাঠককে গভীরভাবে চিন্তা করতে বাধ্য করে।",
  "year": 2026,
  "priority": 5
},
{
  "id": "mansur-hallajer-sotto-bolar-shokh",
  "title": "মনসুর হাল্লাজের সত্য বলার শখ (PDF)",
  "author": "আরিফ রহমান",
  "cover": "https://m.media-amazon.com/images/S/compressed.photo.goodreads.com/books/1708510461i/208941965.jpg",
  "description": "সুফি সাধক মনসুর হাল্লাজের জীবন, দর্শন এবং তাঁর 'আনাল হক' (আমিই সত্য) বাণীর অন্তরালে থাকা আধ্যাত্মিক ও রাজনৈতিক প্রেক্ষাপটকে কেন্দ্র করে এক গভীর ও মননশীল আলোচনা।",
  "categories": ["দর্শন", "ইতিহাস"],
  "status": "পড়বো",
  "storeLink": "https://rkmri.co/AeSoeRe2AMmo/",
  "review": "মনসুর হাল্লাজের জীবনদর্শন ও সত্য প্রকাশের সেই ঐতিহাসিক ও আধ্যাত্মিক পথরেখা জানতে বইটি পড়ার তালিকায় যুক্ত করলাম।",
  "year": 2026,
  "priority": 5
},
{
  "id": "ekguccho-zengolpo",
  "title": "একগুচ্ছ জেনগল্প (PDF)",
  "author": "আরিফ রহমান",
  "cover": "https://rokbucket.rokomari.io/ProductNew20190903/260X372/ekguccho_zen_golpo-Arif_Rahman-5307a-285384.jpg",
  "description": "প্রাচ্যের ঐতিহ্যবাহী জেন দর্শনের গভীর মননশীল, আধ্যাত্মিক ও বুদ্ধিবৃত্তিক ছোট ছোট গল্পের একটি চমৎকার সংকলন, যা মানব মনকে শান্ত করতে এবং জীবনকে ভিন্ন দৃষ্টিকোণ থেকে দেখতে শেখায়।",
  "categories": ["দর্শন", "অনুবাদ ও সংকলন"],
  "status": "পড়া শেষ",
  "storeLink": "https://rkmri.co/TemeT5TeMRMe/",
  "review": "বইটি পড়া শেষ হয়েছে। জেন দর্শনের এই গল্পগুলো খুব সহজ ভাষায় গভীর জীবনবোধ ও মনস্তাত্ত্বিক সত্যকে উন্মোচন করে, যা বেশ উপভোগ্য।",
  "year": 2026,
  "priority": 5
},
{
  "id": "bidrohi-puran",
  "title": "বিদ্রোহী পুরাণ (PDF)",
  "author": "আরিফ রহমান",
  "cover": "https://rokbucket.rokomari.io/ProductNew20190903/260X372/Bidrohi_Puran_-Arif_Rahman-a476d-381899.PNG",
  "description": "ইতিহাস ও পুরাণের পাতায় লুকিয়ে থাকা বিভিন্ন বিপ্লবী চরিত্র, বিদ্রোহ এবং প্রচলিত আখ্যানের অন্তরালে থাকা সামাজিক ও রাজনৈতিক প্রেক্ষাপট নিয়ে এক ভিন্নধর্মী মননশীল আলোচনা।",
  "categories": ["ইতিহাস", "দর্শন"],
  "status": "পড়া শেষ",
  "storeLink": "https://rkmri.co/plIIMMReAp3E/",
  "review": "বইটি পড়া শেষ হয়েছে। পুরাণ ও ইতিহাসের চেনা গল্পগুলোকে এক ভিন্ন ও বিপ্লবী দৃষ্টিকোণ থেকে জানার জন্য এটি একটি দারুণ বই।",
  "year": 2026,
  "priority": 5
},
{
  "id": "religious-mindset",
  "title": "Religious Mindset",
  "author": "সজল রোশন",
  "cover": "https://media.kitabghor.com/products/633/43155/p40si1757676900wljm1pg.jpg",
  "description": "ধর্মীয় মনস্তত্ত্ব, বিশ্বাস ও আধুনিক জীবনযাত্রার নানামুখী সংকটের মাঝে একজন মুমিনের চিন্তাভাবনা ও মানসিকতা কেমন হওয়া উচিত, তা নিয়ে এক গভীর ও বুদ্ধিবৃত্তিক আলোচনা।",
  "categories": ["ধর্ম", "মনস্তত্ত্ব"],
  "status": "পড়া শেষ",
  "storeLink": "https://www.kitabghor.com/products/details/01b967308fcc11f0a44c2a6c60b8696b/religious-mindset.html",
  "review": "বইটি পড়া শেষ হয়েছে। আধুনিক ও সমকালীন প্রেক্ষাপটে ধর্মীয় মানসিকতার স্বরূপ এবং মনস্তাত্ত্বিক বিষয়গুলো বোঝার জন্য এটি একটি চমৎকার বই।",
  "year": 2026,
  "priority": 5
},
{
  "id": "religious-mindset-2-nabir-proggaya",
  "title": "Religious Mindset 2: নবীর প্রজ্ঞায়",
  "author": "সজল রোশন",
  "cover": "https://media.kitabghor.com/products/633/40811/qukv61741753764xj0o2mp.jpg",
  "description": "ধর্মীয় মনস্তত্ত্ব সিরিজের দ্বিতীয় খণ্ড। রাসুলুল্লাহ (সা.)-এর সুন্নাহ, প্রজ্ঞা এবং তাঁর দেখানো জীবনদর্শনের আলোকে আধুনিক মনস্তাত্ত্বিক জটিলতা ও বুদ্ধিবৃত্তিক সংকটগুলোর সমাধানের এক চমৎকার ও গভীর আলোচনা।",
  "categories": ["ধর্ম", "মনস্তত্ত্ব"],
  "status": "পড়া শেষ",
  "storeLink": "https://www.kitabghor.com/products/details/7b3a10e1fef911efaa9c2a6c60b8696b/religious-mindset-2-nabir-proggaya.html",
  "review": "বইটি পড়া শেষ হয়েছে। রাসুলুল্লাহ (সা.)-এর সীরাত ও প্রজ্ঞার আলোকে সমকালীন মানসিক ও বুদ্ধিবৃত্তিক সংকটগুলো বোঝার জন্য এটি প্রথম খণ্ডের মতোই দারুণ একটি ধারাবাহিক বই।",
  "year": 2026,
  "priority": 5
},
{
  "id": "tawheedbhittik-adhunik-rastrabyabostha",
  "title": "তওহীদভিত্তিক আধুনিক রাষ্ট্রব্যবস্থা",
  "author": "হোসাইন মোহাম্মদ সেলিম",
  "cover": "https://hezbuttawheed.org/wp-content/uploads/elementor/thumbs/1745818892883-r50f6lzq5ug6ttmh12g1b7z7cjphxf8eoxfi0t41z4.jpg",
  "description": "ইসলামের মূল ভিত্তি 'তওহীদ'-এর আদর্শকে কেন্দ্র করে একটি আধুনিক, কল্যাণমুখী ও বৈষম্যহীন রাষ্ট্রব্যবস্থা কীভাবে গড়ে তোলা সম্ভব, তার রূপরেখা ও রাজনৈতিক-সামাজিক দিকনির্দেশনা নিয়ে একটি তাত্ত্বিক আলোচনা।",
  "categories": ["ধর্ম", "রাজনীতি"],
  "status": "পড়া শেষ",
  "storeLink": "https://hezbuttawheed.org/book/tawheedbhittik-adhunik-rastrabyabostha/",
  "review": "বইটি বর্তমানে পড়ছি। তওহীদের আদর্শে আধুনিক রাষ্ট্রকাঠামো পরিচালনার রাজনৈতিক ও ধর্মীয় চিন্তাভাবনাগুলো বেশ গভীরভাবে পর্যবেক্ষণ করছি।",
  "year": 2026,
  "priority": 5
},
{
  "id": "the-lost-islam",
  "title": "The Lost Islam",
  "author": "হমোহাম্মদ বায়াজীদ খান পন্নী",
  "cover": "https://hezbuttawheed.org/wp-content/uploads/elementor/thumbs/the_lost_islam_book-pb2bxra36anmtzkxsbr9k8vmri2779q1rn0j3i27eo.png",
  "description": "ইসলামের প্রকৃত ও গৌরবময় আদর্শ হারিয়ে যাওয়ার ঐতিহাসিক কারণ এবং কীভাবে আজ মুসলিম উম্মাহ প্রকৃত পথ থেকে বিচ্যুত হয়ে নানামুখী সংকটে পতিত হয়েছে, তা নিয়ে এক বিশ্লেষণাত্মক ও সংশোধনমূলক আলোচনা।",
  "categories": ["ধর্ম", "ইতিহাস"],
  "status": "পড়ছি",
  "storeLink": "https://hezbuttawheed.org/book/the-lost-islam/",
  "review": "বইটি বর্তমানে পড়ছি। ইসলামের আদি ও প্রকৃত রূপ এবং বর্তমানের বিচ্যুতিগুলোর তুলনামূলক বিশ্লেষণ বেশ গভীরভাবে অনুধাবন করছি।",
  "year": 2026,
  "priority": 5
},
{
  "id": "al-quraner-bishoivittik-ayat",
  "title": "আল কুরআনের বিষয়ভিত্তিক আয়াত",
  "author": "প্রকৌশলী মইনুল হোসেন",
  "cover": "https://rokbucket.rokomari.io/ProductNew20190903/260X372/b42b1bd5a_69421.jpg",
  "description": "পবিত্র কুরআনের বিভিন্ন আয়াতকে মানবজীবনের প্রাত্যহিক, সামাজিক, ধর্মীয় ও নৈতিক বিষয়ের ওপর ভিত্তি করে সহজভাবে শ্রেণিবদ্ধ ও সংকলিত করা একটি আকর গ্রন্থ, যা নির্দিষ্ট বিষয়ের ওপর কুরআনের নির্দেশনা এক নজরে জানতে সাহায্য করে।",
  "categories": ["ধর্ম", "অনুবাদ ও সংকলন"],
  "status": "পড়বো",
  "storeLink": "https://rkmri.co/TAeIMNeIemeS/",
  "review": "নির্দিষ্ট বিষয়ে পবিত্র কুরআনের সুনির্দিষ্ট দিকনির্দেশনা ও আয়াতগুলো সহজে খুঁজে পেতে এবং তা নিয়ে গবেষণা করতে বইটি পড়ার তালিকায় যুক্ত করলাম।",
  "year": 2026,
  "priority": 5
},
{
  "id": "shane-nuzul",
  "title": "শানে নুযূল",
  "author": "মুফতী মুহাম্মদ শফিউল আলম",
  "cover": "https://rokbucket.rokomari.io/ProductNew20190903/260X372/Shane_Nuzul_-Justice_Mufti_Muhammad_Toki_Osmani-31c3c-433765.jpg",
  "description": "পবিত্র কুরআনের বিভিন্ন সূরা ও আয়াত নাজিল হওয়ার ঐতিহাসিক প্রেক্ষাপট, কারণ এবং ঘটনার নিখুঁত বিবরণ সংবলিত একটি অত্যন্ত নির্ভরযোগ্য গ্রন্থ, যা আয়াতের সঠিক মর্মার্থ ও হুকুম অনুধাবন করতে সাহায্য করে।",
  "categories": ["ধর্ম"],
  "status": "পড়বো",
  "storeLink": "https://rkmri.co/SIpe2e2S0Ae0/",
  "review": "কুরআনের আয়াত নাজিল হওয়ার পেছনের ঐতিহাসিক প্রেক্ষাপট ও শানে নুযূল বিস্তারিতভাবে জানার জন্য বইটি পড়ার তালিকায় যুক্ত করলাম।",
  "year": 2026,
  "priority": 5
},
{
  "id": "hadither-name-jaliyati",
  "title": "হাদিসের নামে জালিয়াতি",
  "author": "ড. খোন্দকার আব্দুল্লাহ জাহাঙ্গীর",
  "cover": "https://rokbucket.rokomari.io/ProductNew20190903/260X372/40113bde4_75367.jpg",
  "description": "আমাদের সমাজে প্রচলিত বিভিন্ন জাল ও ভিত্তিহীন হাদিস, বানোয়াট কিচ্ছা-কাহিনী এবং মনগড়া ধর্মীয় বিশ্বাসের অসারতা প্রমাণ করে সহীহ সুন্নাহর আলো ছড়ানোর ক্ষেত্রে একটি অত্যন্ত গুরুত্বপূর্ণ ও গবেষণাধর্মী আকর গ্রন্থ।",
  "categories": ["ধর্ম"],
  "status": "পড়া শেষ",
  "storeLink": "https://rkmri.co/0Me3mmem5yTl/",
  "review": "বইটি আগে পড়া শেষ হয়েছে। সমাজে প্রচলিত জাল হাদিস ও ধর্মীয় কুসংস্কারগুলো চিহ্নিত করে সহীহ ও বানোয়াট হাদিসের পার্থক্য বোঝার জন্য এটি একটি অসাধারণ গবেষণামূলক বই।",
  "year": 2026,
  "priority": 5
},
{
  "id": "dhormobayboshaye-fande",
  "title": "ধর্মব্যবসার ফাঁদে",
  "author": "হোসাইন মোহাম্মদ সেলিম",
  "cover": "https://hezbuttawheed.org/wp-content/uploads/elementor/thumbs/dhormobebsar-faade-pb2bxniqeyihjjqeea4ra9tsdykqchb4f4el6e7s3k.png",
  "description": "ধর্মকে পুঁজি করে কায়েমি স্বার্থান্বেষী মহলের ব্যবসা, ধর্মের নামে কুসংস্কার ও অপব্যাখ্যার মাধ্যমে সাধারণ মানুষকে বিভ্রান্ত করার বিভিন্ন কৌশল এবং এর থেকে মুক্তির উপায় নিয়ে এক সচেতনতামূলক আলোচনা।",
  "categories": ["ধর্ম"],
  "status": "পড়া শেষ",
  "storeLink": "https://hezbuttawheed.org/book/ধর্মব্যবসার-ফাঁদে/",
  "review": "বইটি পড়া শেষ হয়েছে। ধর্মের নামে সমাজে প্রচলিত বিভিন্ন ব্যবসা ও অপকৌশল সম্পর্কে সচেতন হতে এবং ইসলামের প্রকৃত শিক্ষা বুঝতে এটি একটি সময়োপযোগী বই।",
  "year": 2026,
  "priority": 5
},
{
  "id": "misquoting-muhammad",
  "title": "Misquoting Muhammad",
  "author": "Dr. Jonathan A.C. Brown",
  "cover": "https://rokbucket.rokomari.io/ProductNew20190903/260X372/Misquoting_Muhammad_-Dr_Jonathan_AC_Brown-effbd-455090.jpg",
  "description": "ইসলামী ঐতিহ্যে হাদিস শাস্ত্রের সংকলন, ব্যাখ্যা এবং সমকালীন প্রেক্ষাপটে এর অপপ্রয়োগ ও অপব্যাখ্যার এক গভীর ও বুদ্ধিবৃত্তিক বিশ্লেষণ। পশ্চিমা ও আধুনিক সংশয়বাদের জবাবে এটি একটি অনন্য গবেষণামূলক কাজ।",
  "categories": ["ধর্ম", "ইতিহাস"],
  "status": "পড়া শেষ",
  "storeLink": "https://rkmri.co/MA25m32EMeRI/",
  "review": "হাদিস শাস্ত্রের নির্ভরযোগ্যতা এবং আধুনিক বিশ্বে এর অপব্যাখ্যার জবাব জানতে এই গুরুত্বপূর্ণ গবেষণামূলক বইটি পড়ার তালিকায় যুক্ত করলাম।",
  "year": 2026,
  "priority": 5
},
{
  "id": "after-the-prophet",
  "title": "After the Prophet",
  "author": "Lesley Hazleton",
  "cover": "https://wafilife-media.wafilife.com/uploads/2023/02/after-the-prophet.jpg",
  "description": "রাসুলুল্লাহ (সা.)-এর ওফাতের পরবর্তী সময়ে মুসলিম উম্মাহর ঐতিহাসিক প্রেক্ষাপট, রাজনৈতিক নেতৃত্ব এবং শিয়া-সুন্নি বিভাজনের সূচনা ও তার মনস্তাত্ত্বিক কারণগুলোর এক চমৎকার ও নিরপেক্ষ আখ্যান।",
  "categories": ["ধর্ম","ইতিহাস", "রাজনীতি"],
  "status": "পড়া শেষ",
  "storeLink": "https://rkmri.co/AeySRNeMMMNe/",
  "review": "ইসলামের ইতিহাসের অন্যতম এক মোড় ঘোরানো অধ্যায় এবং শিয়া-সুন্নি বিভাজনের ঐতিহাসিক রূপরেখাটি বিস্তারিত জানতে বইটি পড়ার তালিকায় যুক্ত করলাম।",
  "year": 2026,
  "priority": 5
},
{
  "id": "the-prophet",
  "title": "The Prophet",
  "author": "Lesley Hazleton",
  "cover": "https://baatighar.com/web/image/product.product/32225/image_1024",
  "description": "আলমুস্তাফা নামক এক সুফি চরিত্রের বিদায়লগ্নে দেওয়া ২৬টি কাব্যিক ও দার্শনিক প্রবচনের এক কালজয়ী সংকলন। প্রেম, বিয়ে, সন্তান, কর্ম, সুখ-দুঃখ এবং মৃত্যুসহ জীবনের মৌলিক অনুষঙ্গগুলো নিয়ে এতে এক গভীর ও আধ্যাত্মিক জীবনদর্শন উন্মোচিত হয়েছে।",
  "categories": ["দর্শন", "সাহিত্য ও ফিকশন"],
  "status": "পড়া শেষ",
  "storeLink": "https://rkmri.co/mo0TMpeTeEyl/",
  "review": "বইটি পড়া শেষ হয়েছে। খলিল জিবরানের এই কালজয়ী সৃষ্টিটি জীবন, সমাজ ও দর্শনের গভীরতম সত্যগুলোকে অসাধারণ কাব্যিক ও মননশীল ভাষায় প্রকাশ করে, যা বারবার পড়ার মতো।",
  "year": 2026,
  "priority": 5
},
{
  "id": "al-quran-bangla-mormobani",
  "title": "আল কুরআন বাংলা মর্মবাণী",
  "author": "_",
  "cover": "https://rokbucket.rokomari.io/ProductNew20190903/260X372/20100612dc14_117496.gif",
  "description": "পবিত্র কুরআনের আরবী ব্যাকরণ ও আক্ষরিক অনুবাদের জটিলতা এড়িয়ে সাধারণ মানুষের বোধগম্য, প্রাঞ্জল এবং সাবলীল বাংলা ভাষায় এর অন্তর্নিহিত ভাবার্থ বা মর্মবাণী ফুটিয়ে তোলার একটি অত্যন্ত জনপ্রিয় ও সমাদৃত প্রয়াস।",
  "categories": ["ধর্ম", "অনুবাদ ও সংকলন"],
  "status": "পড়া শেষ",
  "storeLink": "https://rkmri.co/A5SN5mo0EmeA/",
  "review": "পড়া শেষ হয়েছে। সাধারণ ও সহজ বাংলায় পবিত্র কুরআনের বাণীবহুল মর্মার্থ অনুধাবন করার জন্য এটি অত্যন্ত চমৎকার এবং হৃদয়গ্রাহী একটি অনুবাদ।",
  "year": 2026,
  "priority": 5
},
{
  "id": "show-your-work",
  "title": "Show Your Work!",
  "author": "Austin Kleon",
  "cover": "https://rokbucket.rokomari.io/ProductNew20190903/260X372/Show_Your_Work-Austin_Kleon-82019-147119.jpg",
  "description": "নিজের কাজ, সৃজনশীলতা এবং আইডিয়াগুলো কীভাবে দুনিয়ার সামনে তুলে ধরতে হয়, কীভাবে পর্দার পেছনের কাজের প্রক্রিয়া বা প্রসেস শেয়ার করে সমমনা মানুষের সাথে একটি নেটওয়ার্ক গড়ে তোলা যায়—তা নিয়ে ১০টি চমৎকার ও বাস্তবমুখী টিপস সংবলিত একটি দারুণ গাইডবুক।",
  "categories": ["আত্মউন্নয়ন ও অনুপ্রেরণা", "ব্যবসা ও ক্যারিয়ার"],
  "status": "পড়া শেষ",
  "storeLink": "https://rkmri.co/AmEyoAoASyAR/",
  "review": "বইটি পড়া শেষ হয়েছে। নিজের কাজ বা ক্রিয়েটিভিটিকে লুকিয়ে না রেখে কীভাবে মানুষের সামনে আনা যায় এবং সেলফ-প্রোমোশনের ভয় কাটিয়ে নেটওয়ার্কিং তৈরি করা যায়, তা জানার জন্য এটি অত্যন্ত কার্যকরী একটি বই।",
  "year": 2026,
  "priority": 5
},
{
  "id": "steal-like-an-artist",
  "title": "Steal Like an Artist",
  "author": "Austin Kleon",
  "cover": "https://diwanegypt.com/wp-content/uploads/2022/06/9780761185680.jpg",
  "description": "ডিজিটাল যুগের সৃজনশীলতার ওপর লেখা একটি দারুণ ম্যানিফেস্টো, যা নতুন কিছু তৈরির চিরাচরিত ভয় দূর করে। অন্যের কাজ থেকে অনুপ্রেরণা নিয়ে কীভাবে নিজের মৌলিক ও সৃজনশীল সত্ত্বাকে ফুটিয়ে তোলা যায়, তা নিয়ে ১০টি রূপান্তরমূলক নির্দেশনা সংবলিত বই।",
  "categories": ["আত্মউন্নয়ন ও অনুপ্রেরণা", "শিল্প ও সংস্কৃতি"],
  "status": "পড়া শেষ",
  "storeLink": "https://rkmri.co/l0pmoTlT2pTM/",
  "review": "বইটি পড়া শেষ হয়েছে। সৃজনশীল কাজের ক্ষেত্রে অনুপ্রেরণা পাওয়ার এবং নিজের ভেতরের ইউনিক ক্রিয়েটিভিটি প্রকাশ করার জন্য এটি একটি অসাধারণ ও অত্যন্ত উদ্দীপনামূলক গাইডবুক।",
  "year": 2026,
  "priority": 5
},
{
  "id": "mans-search-for-meaning",
  "title": "Man's Search for Meaning",
  "author": "Viktor E. Frankl",
  "cover": "https://cdn.shopify.com/s/files/1/0625/6679/3413/files/Man_s_20Search_20for_20Meaning.jpg?v=1716721738",
  "description": "দ্বিতীয় বিশ্বযুদ্ধের সময় নাৎসি কনসেন্ট্রেশন ক্যাম্পে বন্দী থাকা একজন মনোরোগ বিশেষজ্ঞের মর্মস্পর্শী অভিজ্ঞতা এবং লোগোথেরাপির ওপর ভিত্তি করে লেখা একটি কালজয়ী মনস্তাত্ত্বিক গ্রন্থ। চরম দুঃখ-কষ্টের মাঝেও মানুষ কীভাবে জীবনের অর্থ খুঁজে পায়, তা-ই এখানে উন্মোচিত হয়েছে।",
  "categories": ["মনস্তত্ত্ব", "দর্শন", "ইতিহাস"],
  "status": "পড়বো",
  "storeLink": "https://rkmri.co/MIMSINASyI30/",
  "review": "মানুষের মনস্তত্ত্ব এবং জীবনের প্রকৃত অর্থ খোঁজার এক অবিস্মরণীয় আখ্যান জানতে এই বিশ্বখ্যাত কালজয়ী বইটি পড়ার তালিকায় যুক্ত করলাম।",
  "year": 2026,
  "priority": 5
},
{
  "id": "the-psychology-of-money",
  "title": "The Psychology of Money",
  "author": "Morgan Housel",
  "cover": "https://rokbucket.rokomari.io/ProductNew20190903/260X372/The_Psychology_Of_Money-Morgan_Housel-6e6e5-325590.jpg",
  "description": "টাকা বা অর্থ উপার্জনের ক্ষেত্রে প্রাতিষ্ঠানিক বা গাণিতিক দক্ষতার চেয়ে মানুষের আচরণ, মনস্তত্ত্ব এবং দৃষ্টিভঙ্গি কীভাবে কাজ করে, তা ১৯টি ছোট গল্পের মাধ্যমে চমৎকারভাবে বিশ্লেষণ করা একটি বিশ্বখ্যাত গ্রন্থ।",
  "categories": ["মনস্তত্ত্ব", "ব্যবসা ও ক্যারিয়ার"],
  "status": "পড়বো",
  "storeLink": "https://rkmri.co/M5p0NTSNmER3/",
  "review": "অর্থের পেছনে কাজ করা মানুষের আচরণগত মনস্তত্ত্ব এবং জীবনকে সুন্দরভাবে পরিচালনা করার বাস্তবমুখী কৌশলগুলো জানতে বইটি পড়ার তালিকায় যুক্ত করলাম।",
  "year": 2026,
  "priority": 5
},
{
  "id": "how-to-talk-to-anyone",
  "title": "How to Talk to Anyone",
  "author": "Leil Lowndes",
  "cover": "https://rokbucket.rokomari.io/ProductNew20190903/260X372/39669fe90_100907.jpg",
  "description": "যোগাযোগ দক্ষতা বা কমিউনিকেশন স্কিল উন্নত করার ৯২টি চমৎকার ও বাস্তবমুখী কৌশল সংবলিত একটি বিশ্বখ্যাত গাইডবুক। প্রথম দেখায় মানুষের মন জয় করা, বডি ল্যাঙ্গুয়েজের সঠিক ব্যবহার এবং যেকোনো সামাজিক বা ব্যবসায়িক আড্ডায় আত্মবিশ্বাসের সাথে কথা বলার উপায় এতে আলোচনা করা হয়েছে।",
  "categories": ["আত্মউন্নয়ন ও অনুপ্রেরণা", "মনস্তত্ত্ব"],
  "status": "পড়বো",
  "storeLink": "https://rkmri.co/T2mMMl3AA05R/",
  "review": "যেকোনো মানুষের সাথে সহজে মিশে যাওয়ার, চমৎকারভাবে কথা বলার এবং নিজের কমিউনিকেশন স্কিলকে আরও সুনিপুণ করার কার্যকরী কৌশলগুলো শিখতে বইটি পড়ার তালিকায় যুক্ত করলাম।",
  "year": 2026,
  "priority": 5
}
  
]
